Workbook
Name Deal_Type: [1]Inputs!$H$12
Name IRR: [1]Inputs!$F$45
Name IRR_wo: [1]Inputs!$G$45
Name Org_Struct: [1]Inputs!$H$11
Name print_all: 'Pro Forma Financials'!print_all
Name print_all: [0]!print_all
Name Project_Name: [1]Inputs!$H$9
Name Strat: [1]Inputs!$H$10
Name Target: [1]Inputs!$H$8
Name Tax_rate: [1]Inputs!$H$60
Name TTM_Date: [1]Inputs!$H$13
Name WACC: [1]Inputs!$H$73

Sheet Project Rocky
A5: Project Rocky
A7: Finance & Operations Diligence

Sheet Top Client Accounts
A1: Project Rocky
A2: Top Client Accounts
B4: Client | C4: Premium | D4: Commissions | E4: % of Total | F4: Commentary
A5: 1 | B5: Chandler Trust | C5: 606033.06 | D5: 75754.133 | E5: =D5/$D$128 -> 0.1704834
A6: 2 | B6: Pisces Inc. | C6: 309863 | D6: 38732.875 | E6: =D6/$D$128 -> 0.087167684
A7: 3 | B7: Westerman Family Office | C7: 219003 | D7: 26877.1 | E7: =D7/$D$128 -> 0.060486461
A8: 4 | B8: Marlborough Galleries Inc & Hermes Trust Co | C8: 129085.79 | D8: 16135.724 | E8: =D8/$D$128 -> 0.036313175
A9: 5 | B9: Wind River Trust Company | C9: 93073 | D9: 13745.875 | E9: =D9/$D$128 -> 0.03093486
A10: 6 | B10: Lorenz | C10: 108029 | D10: 13477.005 | E10: =D10/$D$128 -> 0.030329773
A11: 7 | B11: Pendleton Trust Company | C11: 108524 | D11: 13442.475 | E11: =D11/$D$128 -> 0.030252064
A12: 8 | B12: EBOR (WSG(PTC)) | C12: 106777 | D12: 12813.24 | E12: =D12/$D$128 -> 0.028835981
A13: 9 | B13: TEFAF | C13: 52019 | D13: 12487.2 | E13: =D13/$D$128 -> 0.028102234
A14: 10 | B14: A7P | C14: 95578 | D14: 11947.25 | E14: =D14/$D$128 -> 0.026887085
A15: 11 | B15: Astra Management & Astra PTC | C15: 93392 | D15: 11674 | E15: =D15/$D$128 -> 0.026272141
A16: 12 | B16: Madsen Assets | C16: 88594 | D16: 11074.25 | E16: =D16/$D$128 -> 0.024922413
... A24: 20 | B24: Investors Preferred | C24: 52673.66 | D24: 6142.9309 | E24: =D24/$D$128 -> 0.013824563
A25: 21 | B25: Saul Costa | D25: 5000 | E25: =D25/$D$128 -> 0.011252416
A26: 22 | B26: Steven A. Braun | C26: 38057 | D26: 4757.135 | E26: =D26/$D$128 -> 0.010705852
A27: 23 | B27: Baysore & Christian | C27: 44677 | D27: 4740.71 | E27: =D27/$D$128 -> 0.010668888
A28: 24 | B28: Fortius Metals Inc | C28: 47379.57 | D28: 4737.957 | E28: =D28/$D$128 -> 0.010662693
A29: 25 | B29: Center of the Golden One | C29: 13295 | D29: 4661.875 | E29: =D29/$D$128 -> 0.010491471
A30: 26 | B30: Herman Smith | C30: 36200 | D30: 4525 | E30: =D30/$D$128 -> 0.010183436
A31: 27 | B31: Corvalier Trust Company (Whold Co.) | C31: 35469 | D31: 4433.625 | E31: =D31/$D$128 -> 0.0099777985
A32: 28 | B32: Loyal Trust 2 - Hunt Brothers | C32: 96034 | D32: 4393.5 | E32: =D32/$D$128 -> 0.0098874978
A33: 29 | B33: Trustee Services Group | C33: 29782 | D33: 3722.75 | E33: =D33/$D$128 -> 0.0083779862
A34: 30 | B34: Lotus Fiduciary | C34: 29665 | D34: 3677.775 | E34: =D34/$D$128 -> 0.0082767708
A35: 31 | B35: Edelweiss V LLC | C35: 28000 | D35: 3500 | E35: =D35/$D$128 -> 0.0078766911
A36: 32 | B36: Manton Foundation | C36: 26623 | D36: 3327.885 | E36: =D36/$D$128 -> 0.0074893492
A37: 33 | B37: Li-Costa Living Trust | C37: 25000 | D37: 3125 | E37: =D37/$D$128 -> 0.0070327599
... A97: 93 | B97: Center of the Golden One (Miracle of Love) | C97: 595 | D97: 74.38 | E97: =D97/$D$128 -> 0.00016739094
A98: 94 | B98: Thomas John (TJ) Schrette | C98: 3125 | E98: =D98/$D$128 -> 0
A99: 95 | B99: ATFO, LLC | C99: 13125 | E99: =D99/$D$128 -> 0
A100: 96 | B100: Atinaw, LLC | C100: 8925 | E100: =D100/$D$128 -> 0
A101: 97 | B101: Chris Utecht | C101: 7313 | E101: =D101/$D$128 -> 0
A102: 98 | B102: Dakota Hill (PTC) | C102: 20992 | E102: =D102/$D$128 -> 0
A103: 99 | B103: Dallas College Enterprise Ventures | C103: 21250 | E103: =D103/$D$128 -> 0
A104: 100 | B104: David Amar | C104: 15308 | E104: =D104/$D$128 -> 0
A105: 101 | B105: David Holland (Holland Trustees) | C105: 4078 | E105: =D105/$D$128 -> 0
A106: 102 | B106: Diana Beinart | C106: 2500 | E106: =D106/$D$128 -> 0
A107: 103 | B107: Don Parkhill | C107: 2500 | E107: =D107/$D$128 -> 0
A108: 104 | B108: Duncan & John C Schmidt | C108: 2625 | E108: =D108/$D$128 -> 0
A109: 105 | B109: Edward White & Tina Moss as Trustee for Jerome Moss | C109: 46552 | E109: =D109/$D$128 -> 0
... A125: 121 | B125: Sonic Boom (PTC) | C125: 17608 | E125: =D125/$D$128 -> 0
B126: Top 15 Accounts | C126: =SUM(C5:C19) -> 2269070.9 | D126: =SUM(D5:D19) -> 287680.63 | E126: =D126/$D$128 -> 0.64742042
B127: All Other Accounts | C127: =C128-C126 -> 1727678.3 | D127: =D128-D126 -> 156668.39 | E127: =D127/$D$128 -> 0.35257958
B128: Total Accounts | C128: =SUM(C5:C125) -> 3996749.1 | D128: =SUM(D5:D125) -> 444349.02 | E128: =D128/$D$128 -> 1

Sheet Top Wholesalers
A1: Project Rocky
A2: Top Wholesalers
B4: Wholesaler | C4: Premium | D4: Commissions | E4: % of Total | F4: Commentary
A5: 1 | B5: ARC | C5: 3117457.6 | D5: 344560.69 | E5: =D5/$D$14 -> 0.77542803
A6: 2 | B6: RT & RTS | C6: 627430.96 | D6: 58780.952 | E6: =D6/$D$14 -> 0.13228554
A7: 3 | B7: Element | C7: 138290 | D7: 14317.925 | E7: =D7/$D$14 -> 0.032222249
A8: 4 | B8: Affinity | C8: 45706 | D8: 6855.9 | E8: =D8/$D$14 -> 0.015429088
A9: 5 | B9: CRC | C9: 43167.57 | D9: 4316.757 | E9: =D9/$D$14 -> 0.009714789
A10: 6 | B10: Pearl | C10: 14535 | D10: 1308.15 | E10: =D10/$D$14 -> 0.0029439696
A11: 7 | B11: ProSight | C11: 6313 | D11: 631.3 | E11: =D11/$D$14 -> 0.00142073
B12: Top Wholesalers | C12: =SUM(C5:C11) -> 3992900.1 | D12: =SUM(D5:D11) -> 430771.67 | E12: =D12/$D$14 -> 0.9694444
B13: All Other | C13: =C14-C12 -> 3849 | D13: =D14-D12 -> 13577.35 | E13: =D13/$D$14 -> 0.030555598
B14: Total | C14: ='Top Client Accounts'!C128 -> 3996749.1 | D14: ='Top Client Accounts'!D128 -> 444349.02 | E14: =D14/$D$14 -> 1

Sheet Pro Forma Financials
A1: Project Rocky
A2: Pro Forma Financials
C4: 46174 | F4: Pro Forma | H4: MMA
A5: $ in actual | B5: 2025 | C5: TTM | F5: Adjustments | H5: Pro Forma | J5: Notes to Pro forma
A6: Revenue
A7: Sales | B7: 351963.13 | C7: ='June-26 TTM '!B7-64000 -> 505203.54 | F7: =SUM('Book of Business'!H312:H316)-'Pro Forma Financials'!C8-C18 -> 86628.173 | H7: =C7+F7 -> 591831.71 | J7: MMA: Delta between Book of Business (Production Report) and P&L
A8: P&C Commissions | B8: 351963.13 | C8: =SUBTOTAL(9,C7:C7) -> 505203.54 | F8: =SUBTOTAL(9,F7:F7) -> 86628.173 | H8: =SUBTOTAL(9,H7:H7) -> 591831.71
A11: Gross Commissions & Fees | B11: 351963.13 | C11: =SUBTOTAL(9,C$7:C$9) -> 505203.54 | F11: =SUBTOTAL(9,F$7:F$9) -> 86628.173 | H11: =SUBTOTAL(9,H$7:H$9) -> 591831.71
B13: 0 | C13: =IFERROR(INDEX([1]PF_Input!$B$9:$F$89,MATCH($A13,[1]PF_Input!$B$9:$B$89,0),MATCH(C$3,[1]PF_Input!$B$5:$F$5,0)),0) -> 0 | F13: 0 | H13: =C13+F13 -> 0
A14: Sub-Broker Expense | B14: 0 | C14: =SUBTOTAL(9,C13:C13) -> 0 | F14: =SUBTOTAL(9,F13:F13) -> 0 | H14: =SUBTOTAL(9,H13:H13) -> 0
A16: Net Commissions & Fees | B16: 351963.13 | C16: =SUBTOTAL(9,C$7:C$14) -> 505203.54 | F16: =SUBTOTAL(9,F$7:F$14) -> 86628.173 | H16: =SUBTOTAL(9,H$7:H$14) -> 591831.71
A18: Beazley Contingent | B18: 64000 | C18: 64000 | H18: =C18+F18 -> 64000
A19: Contingent Income | B19: 64000 | C19: =SUBTOTAL(9,C18:C18) -> 64000 | F19: =SUBTOTAL(9,F18:F18) -> 0 | H19: =SUBTOTAL(9,H18:H18) -> 64000
A21: Premium Finance Income | B21: 0 | C21: =IFERROR(INDEX([1]PF_Input!$B$9:$F$89,MATCH($A21,[1]PF_Input!$B$9:$B$89,0),MATCH(C$3,[1]PF_Input!$B$5:$F$5,0)),0) -> 0 | F21: 0 | H21: =C21+F21 -> 0
A22: Investment Income | B22: 0 | C22: =SUBTOTAL(9,C21:C21) -> 0 | F22: =SUBTOTAL(9,F21:F21) -> 0 | H22: =SUBTOTAL(9,H21:H21) -> 0
A24: Convenience Fee Income | B24: 0 | C24: ='June-26 TTM '!B52 -> 205 | F24: 0 | H24: =C24+F24 -> 205
A25: Miscellaneous Income | B25: 0 | C25: =SUBTOTAL(9,C24:C24) -> 205 | F25: =SUBTOTAL(9,F24:F24) -> 0 | H25: =SUBTOTAL(9,H24:H24) -> 205
A27: Other Income | B27: 64000 | C27: =SUBTOTAL(9,C18:C25) -> 64205 | F27: =SUBTOTAL(9,F18:F25) -> 0 | H27: =SUBTOTAL(9,H18:H25) -> 64205
A28: Total Revenue | B28: 415963.13 | C28: =SUBTOTAL(9,C7:C25) -> 569408.54 | F28: =SUBTOTAL(9,F7:F25) -> 86628.173 | H28: =SUBTOTAL(9,H7:H25) -> 656036.71
A30: Expenses
A31: Officers Salary | B31: 200002.16 | C31: ='June-26 TTM '!B35 -> 183335.48 | F31: ='Employee Roster'!S8-'Pro Forma Financials'!C31 -> 66664.52 | H31: =C31+F31 -> 250000 | J31: MMA: Set Judy to go forward compensation structure
A32: Shareholders | B32: 200002.16 | C32: =SUBTOTAL(9,C31:C31) -> 183335.48 | F32: =SUBTOTAL(9,F31:F31) -> 66664.52 | H32: =SUBTOTAL(9,H31:H31) -> 250000
B35: 0 | C35: =IFERROR(INDEX([1]PF_Input!$B$9:$F$89,MATCH($A35,[1]PF_Input!$B$9:$B$89,0),MATCH(C$3,[1]PF_Input!$B$5:$F$5,0)),0) -> 0 | F35: 0
B36: 0 | C36: =IFERROR(INDEX([1]PF_Input!$B$9:$F$89,MATCH($A36,[1]PF_Input!$B$9:$B$89,0),MATCH(C$3,[1]PF_Input!$B$5:$F$5,0)),0) -> 0 | F36: 0
A37: Staff Wages | B37: 122550.59 | C37: ='June-26 TTM '!B38 -> 124914.82 | F37: ='Employee Roster'!S24-'Pro Forma Financials'!C37 -> -14664.82 | H37: =C37+F37 -> 110250 | J37: MMA: Set to salary roster
A38: Staff & Support | B38: 122550.59 | C38: =SUBTOTAL(9,C35:C37) -> 124914.82 | F38: =SUBTOTAL(9,F35:F37) -> -14664.82 | H38: =SUBTOTAL(9,H35:H37) -> 110250
A40: Compensation Expense | B40: 322552.75 | C40: =SUBTOTAL(9,C31:C38) -> 308250.3 | F40: =SUBTOTAL(9,F31:F38) -> 51999.7 | H40: =SUBTOTAL(9,H31:H38) -> 360250
B42: 0 | C42: =IFERROR(INDEX([1]PF_Input!$B$9:$F$89,MATCH($A42,[1]PF_Input!$B$9:$B$89,0),MATCH(C$3,[1]PF_Input!$B$5:$F$5,0)),0) -> 0 | F42: 0
B43: 0 | C43: =IFERROR(INDEX([1]PF_Input!$B$9:$F$89,MATCH($A43,[1]PF_Input!$B$9:$B$89,0),MATCH(C$3,[1]PF_Input!$B$5:$F$5,0)),0) -> 0 | F43: 0
A44: Health Insurance | B44: 0 | C44: =IFERROR(INDEX([1]PF_Input!$B$9:$F$89,MATCH($A44,[1]PF_Input!$B$9:$B$89,0),MATCH(C$3,[1]PF_Input!$B$5:$F$5,0)),0) -> 0 | F44: ='Employee Roster'!AC26 -> 34800 | H44: =C44+F44 -> 34800 | J44: MMA: Set to MMA PCS National benefits
A45: Medical Insurance | B45: 0 | C45: =SUBTOTAL(9,C42:C44) -> 0 | F45: =SUBTOTAL(9,F42:F44) -> 34800 | H45: =SUBTOTAL(9,H42:H44) -> 34800
B47: 0 | C47: =IFERROR(INDEX([1]PF_Input!$B$9:$F$89,MATCH($A47,[1]PF_Input!$B$9:$B$89,0),MATCH(C$3,[1]PF_Input!$B$5:$F$5,0)),0) -> 0 | F47: 0
B48: 0 | C48: =IFERROR(INDEX([1]PF_Input!$B$9:$F$89,MATCH($A48,[1]PF_Input!$B$9:$B$89,0),MATCH(C$3,[1]PF_Input!$B$5:$F$5,0)),0) -> 0 | F48: 0
A49: Payroll Taxes | B49: 26816.6 | C49: ='June-26 TTM '!B37 -> 23961.38 | F49: ='Employee Roster'!AA26-'Pro Forma Financials'!C49 -> -463.255 | H49: =C49+F49 -> 23498.125 | J49: MMA: Recalculate payroll taxes
A50: Payroll Taxes | B50: 26816.6 | C50: =SUBTOTAL(9,C47:C49) -> 23961.38 | F50: =SUBTOTAL(9,F47:F49) -> -463.255 | H50: =SUBTOTAL(9,H47:H49) -> 23498.125
B52: 0 | C52: =IFERROR(INDEX([1]PF_Input!$B$9:$F$89,MATCH($A52,[1]PF_Input!$B$9:$B$89,0),MATCH(C$3,[1]PF_Input!$B$5:$F$5,0)),0) -> 0 | F52: 0
B53: 0 | C53: =IFERROR(INDEX([1]PF_Input!$B$9:$F$89,MATCH($A53,[1]PF_Input!$B$9:$B$89,0),MATCH(C$3,[1]PF_Input!$B$5:$F$5,0)),0) -> 0 | F53: 0
A54: Employee Retirement Plans | B54: 1850 | C54: =IFERROR(INDEX([1]PF_Input!$B$9:$F$89,MATCH($A54,[1]PF_Input!$B$9:$B$89,0),MATCH(C$3,[1]PF_Input!$B$5:$F$5,0)),0) -> 0 | F54: ='Employee Roster'!AB26 -> 12200 | H54: =C54+F54 -> 12200 | J54: MMA: Set to MMA National 401k plan (50% match up to 8% of base salary, effectively 4%)
A55: Retirement | B55: 1850 | C55: =SUBTOTAL(9,C52:C54) -> 0 | F55: =SUBTOTAL(9,F52:F54) -> 12200 | H55: =SUBTOTAL(9,H52:H54) -> 12200
A57: Benefits Expense | B57: 28666.6 | C57: =SUBTOTAL(9,C42:C55) -> 23961.38 | F57: =SUBTOTAL(9,F42:F55) -> 46536.745 | H57: =SUBTOTAL(9,H42:H55) -> 70498.125
A58: Compensation & Benefits | B58: 351219.35 | C58: =SUBTOTAL(9,C31:C55) -> 332211.68 | F58: =SUBTOTAL(9,F31:F55) -> 98536.445 | H58: =SUBTOTAL(9,H31:H55) -> 430748.12
A60: Meals | B60: 3479.88 | C60: ='June-26 TTM '!B26 -> 5098 | F60: 0 | H60: =C60+F60 -> 5098
A61: Meals with clients | B61: 33.75 | C61: ='June-26 TTM '!B27 -> 18.05 | F61: 0 | H61: =C61+F61 -> 18.05
A62: Travel | B62: 791.78 | C62: ='June-26 TTM '!B44 -> 791.78 | F62: 0 | H62: =C62+F62 -> 791.78
A63: Airfare | B63: 6890.65 | C63: ='June-26 TTM '!B45 -> 14971.31 | F63: 0 | H63: =C63+F63 -> 14971.31
A64: Hotels | B64: 5738.11 | C64: ='June-26 TTM '!B46 -> 5567.91 | F64: 0 | H64: =C64+F64 -> 5567.91
A65: Taxis or shared rides | B65: 1779.1 | C65: ='June-26 TTM '!B47 -> 2018.49 | F65: 0 | H65: =C65+F65 -> 2018.49
A66: Parking & Tolls | B66: 94 | C66: ='June-26 TTM '!B56 -> 175 | F66: 0 | H66: =C66+F66 -> 175
A67: Travel & Entertainment | B67: 18807.27 | C67: =SUBTOTAL(9,C60:C66) -> 28640.54 | F67: =SUBTOTAL(9,F60:F66) -> 0 | H67: =SUBTOTAL(9,H60:H66) -> 28640.54
A69: Vehicle gas & fuel | B69: 0 | C69: ='June-26 TTM '!B57 -> 52.15 | F69: 0 | H69: =C69+F69 -> 52.15
A70: Automobile | B70: 0 | C70: =SUBTOTAL(9,C69:C69) -> 52.15 | F70: =SUBTOTAL(9,F69:F69) -> 0 | H70: =SUBTOTAL(9,H69:H69) -> 52.15
B72: 0 | C72: =IFERROR(INDEX([1]PF_Input!$B$9:$F$89,MATCH($A72,[1]PF_Input!$B$9:$B$89,0),MATCH(C$3,[1]PF_Input!$B$5:$F$5,0)),0) -> 0 | F72: 0 | H72: =C72+F72 -> 0
B73: 0 | C73: =IFERROR(INDEX([1]PF_Input!$B$9:$F$89,MATCH($A73,[1]PF_Input!$B$9:$B$89,0),MATCH(C$3,[1]PF_Input!$B$5:$F$5,0)),0) -> 0 | F73: 0 | H73: =C73+F73 -> 0
A74: Advertising & Marketing | B74: 1280.7 | C74: ='June-26 TTM '!B11 -> 510.76 | F74: 0 | H74: =C74+F74 -> 510.76
A75: Marketing & Advertising | B75: 1280.7 | C75: =SUBTOTAL(9,C72:C74) -> 510.76 | F75: =SUBTOTAL(9,F72:F74) -> 0 | H75: =SUBTOTAL(9,H72:H74) -> 510.76
A77: Sales & Marketing | B77: 20087.97 | C77: =SUBTOTAL(9,C60:C75) -> 29203.45 | F77: =SUBTOTAL(9,F60:F75) -> 0 | H77: =SUBTOTAL(9,H60:H75) -> 29203.45
A79: OFF RENT | B79: 679.78 | C79: ='June-26 TTM '!B43 -> 6122.28 | F79: =18000-C79 -> 11877.72 | H79: =C79+F79 -> 18000 | J79: MMA: Set to cost per head for PCSN Denver office space
A80: Office Expenses | B80: 340.42 | C80: ='June-26 TTM '!B29 -> 340.42 | F80: =-C80 -> -340.42 | H80: =C80+F80 -> 0
B81: 0 | C81: =IFERROR(INDEX([1]PF_Input!$B$9:$F$89,MATCH($A81,[1]PF_Input!$B$9:$B$89,0),MATCH(C$3,[1]PF_Input!$B$5:$F$5,0)),0) -> 0 | F81: 0 | H81: =C81+F81 -> 0
A82: Facilities & Equipment | B82: 1020.2 | C82: =SUBTOTAL(9,C79:C81) -> 6462.7 | F82: =SUBTOTAL(9,F79:F81) -> 11537.3 | H82: =SUBTOTAL(9,H79:H81) -> 18000
A84: Accounting Fees | B84: 5940.56 | C84: ='June-26 TTM '!B23 -> 4007.78 | F84: 0 | H84: =C84+F84 -> 4007.78
A85: Legal Fees | B85: 3948.01 | C85: ='June-26 TTM '!B24 -> 5295.51 | F85: 0 | H85: =C85+F85 -> 5295.51
A86: Legal & accounting services | C86: ='June-26 TTM '!B22 -> 97.85 | H86: =C86+F86 -> 97.85
A87: Professional Services | B87: 3600.36 | C87: ='June-26 TTM '!B40 -> 2705.8 | F87: 0 | H87: =C87+F87 -> 2705.8
A88: Outside Services | B88: 13488.93 | C88: =SUBTOTAL(9,C84:C87) -> 12106.94 | F88: =SUBTOTAL(9,F84:F87) -> 0 | H88: =SUBTOTAL(9,H84:H87) -> 12106.94
B90: 0 | C90: =IFERROR(INDEX([1]PF_Input!$B$9:$F$89,MATCH($A90,[1]PF_Input!$B$9:$B$89,0),MATCH(C$3,[1]PF_Input!$B$5:$F$5,0)),0) -> 0 | F90: 0 | H90: =C90+F90 -> 0
B91: 0 | C91: =IFERROR(INDEX([1]PF_Input!$B$9:$F$89,MATCH($A91,[1]PF_Input!$B$9:$B$89,0),MATCH(C$3,[1]PF_Input!$B$5:$F$5,0)),0) -> 0 | F91: 0 | H91: =C91+F91 -> 0
A92: Software, IT, & Apps | B92: 17124.09 | C92: ='June-26 TTM '!B32 -> 24553.15 | F92: 0 | H92: =C92+F92 -> 24553.15
A93: IT - Communication | B93: 17124.09 | C93: =SUBTOTAL(9,C90:C92) -> 24553.15 | F93: =SUBTOTAL(9,F90:F92) -> 0 | H93: =SUBTOTAL(9,H90:H92) -> 24553.15
A95: Business licenses | B95: 1313.97 | C95: ='June-26 TTM '!B12 -> 1871.7 | F95: 0 | H95: =C95+F95 -> 1871.7
A96: Dues and memberships | B96: 6366 | C96: ='June-26 TTM '!B13 -> 6147 | F96: 0 | H96: =C96+F96 -> 6147
A97: Memberships and subscriptions | B97: 99 | C97: ='June-26 TTM '!B19 -> 99 | F97: 0 | H97: =C97+F97 -> 99
A98: Licenses Subs & Dues | B98: 7778.97 | C98: =SUBTOTAL(9,C95:C97) -> 8117.7 | F98: =SUBTOTAL(9,F95:F97) -> 0 | H98: =SUBTOTAL(9,H95:H97) -> 8117.7
B100: 0 | C100: =IFERROR(INDEX([1]PF_Input!$B$9:$F$89,MATCH($A100,[1]PF_Input!$B$9:$B$89,0),MATCH(C$3,[1]PF_Input!$B$5:$F$5,0)),0) -> 0 | F100: 0 | H100: =C100+F100 -> 0
B101: 0 | C101: =IFERROR(INDEX([1]PF_Input!$B$9:$F$89,MATCH($A101,[1]PF_Input!$B$9:$B$89,0),MATCH(C$3,[1]PF_Input!$B$5:$F$5,0)),0) -> 0 | F101: 0 | H101: =C101+F101 -> 0
A102: Insurance | B102: 3386.02 | C102: ='June-26 TTM '!B21 -> 9381.85 | F102: 0 | H102: =C102+F102 -> 9381.85
A103: Taxes & Business Insurance | B103: 3386.02 | C103: =SUBTOTAL(9,C100:C102) -> 9381.85 | F103: =SUBTOTAL(9,F100:F102) -> 0 | H103: =SUBTOTAL(9,H100:H102) -> 9381.85
B106: 0 | C106: =IFERROR(INDEX([1]PF_Input!$B$9:$F$89,MATCH($A106,[1]PF_Input!$B$9:$B$89,0),MATCH(C$3,[1]PF_Input!$B$5:$F$5,0)),0) -> 0 | F106: 0 | H106: =C106+F106 -> 0
B107: 0 | C107: =IFERROR(INDEX([1]PF_Input!$B$9:$F$89,MATCH($A107,[1]PF_Input!$B$9:$B$89,0),MATCH(C$3,[1]PF_Input!$B$5:$F$5,0)),0) -> 0 | F107: 0 | H107: =C107+F107 -> 0
A108: Continuing Education | B108: 1927.27 | C108: ='June-26 TTM '!B18 -> 7652.27 | F108: 0 | H108: =C108+F108 -> 7652.27
A109: Training | B109: 1927.27 | C109: =SUBTOTAL(9,C106:C108) -> 7652.27 | F109: =SUBTOTAL(9,F106:F108) -> 0 | H109: =SUBTOTAL(9,H106:H108) -> 7652.27
A112: Employee Expense reimbursement | B112: 457.72 | C112: ='June-26 TTM '!B15 -> 457.72 | F112: 0 | H112: =C112+F112 -> 457.72
A113: General business expenses | B113: 14.35 | C113: ='June-26 TTM '!B16 -> 14.35 | F113: 0 | H113: =C113+F113 -> 14.35
A114: Bank fees & service charges | B114: 290.82 | C114: ='June-26 TTM '!B17 -> 242.16 | F114: 0 | H114: =C114+F114 -> 242.16
A115: Office Supplies | B115: 497.17 | C115: ='June-26 TTM '!B30 -> 3389.49 | F115: 0 | H115: =C115+F115 -> 3389.49
A116: Shipping & Postage | B116: 231.11 | C116: ='June-26 TTM '!B31 -> 233.61 | F116: 0 | H116: =C116+F116 -> 233.61
A117: Payroll Fees | B117: 1241.75 | C117: ='June-26 TTM '!B36 -> 1047.1 | F117: 0 | H117: =C117+F117 -> 1047.1
A118: Employee Benefits | B118: 0 | C118: ='June-26 TTM '!B14 -> 4150 | F118: =-C118 -> -4150 | H118: =C118+F118 -> 0 | J118: MMA: Removal of non-recurring expense related to set up of a profit sharing plan
A119: Miscellaneous | B119: 2732.92 | C119: =SUBTOTAL(9,C112:C118) -> 9534.43 | F119: =SUBTOTAL(9,F112:F118) -> -4150 | H119: =SUBTOTAL(9,H112:H118) -> 5384.43
A121: Other Operating Expenses | B121: 47458.4 | C121: =SUBTOTAL(9,C79:C119) -> 77809.04 | F121: =SUBTOTAL(9,F79:F119) -> 7387.3 | H121: =SUBTOTAL(9,H79:H119) -> 85196.34
A123: EBITDA | B123: -2802.59 | C123: =C28-C58-C77-C121 -> 130184.37 | F123: =F28-F58-F77-F121 -> -19295.572 | H123: =H28-H58-H77-H121 -> 110888.8
A124: EBITDA Margin | B124: -0.0067375923 | C124: =C123/C28 -> 0.22863087 | H124: =H123/H28 -> 0.16902834
A126: Depreciation | B126: 0 | C126: =IFERROR(INDEX([1]PF_Input!$B$9:$F$89,MATCH($A126,[1]PF_Input!$B$9:$B$89,0),MATCH(C$3,[1]PF_Input!$B$5:$F$5,0)),0) -> 0 | F126: =H28*1% -> 6560.3671 | H126: =C126+F126 -> 6560.3671
A127: Credit Card Interest | B127: 206 | C127: =IFERROR(INDEX([1]PF_Input!$B$9:$F$89,MATCH($A127,[1]PF_Input!$B$9:$B$89,0),MATCH(C$3,[1]PF_Input!$B$5:$F$5,0)),0) -> 0 | H127: =C127+F127 -> 0
A128: Convenience fee income | B128: -205 | C128: =IFERROR(INDEX([1]PF_Input!$B$9:$F$89,MATCH($A128,[1]PF_Input!$B$9:$B$89,0),MATCH(C$3,[1]PF_Input!$B$5:$F$5,0)),0) -> 0 | H128: =C128+F128 -> 0
A129: Asset Sale Gain/Loss | B129: 0 | C129: =IFERROR(INDEX([1]PF_Input!$B$9:$F$89,MATCH($A129,[1]PF_Input!$B$9:$B$89,0),MATCH(C$3,[1]PF_Input!$B$5:$F$5,0)),0) -> 0 | F129: 0 | H129: =C129+F129 -> 0
A130: EBITDA Expenses | B130: 1 | C130: =SUBTOTAL(9,C126:C129) -> 0 | F130: =SUBTOTAL(9,F126:F129) -> 6560.3671 | H130: =SUBTOTAL(9,H126:H129) -> 6560.3671
A132: Net Operating Income | B132: -2803.59 | C132: =+C123-C130 -> 130184.37 | F132: =+F123-F130 -> -25855.939 | H132: =+H123-H130 -> 104328.43
A134: Per Source | C134: ='June-26 TTM '!B61 -> 130184.37
A135: Check | B135: 0 | C135: =ROUND(C132-C134,0) -> 0

Sheet Book of Business
A1: Insured | B1: Ex. Date | C1: Coverage | D1: Carrier | E1: Wholesaler | F1: Liab Limit | G1: Premium | H1: Commission | I1: Monthly Premium Totals | J1: BP Pymt | K1: IPFS+misc
A2: Pisces | B2: 45658 | C2: PNC | E2: Element | G2: 100000 | H2: 10000
A3: ATFO, LLC | B3: 44562 | C3: TREO | D3: Nomadx | E3: ARC | F3: $1M | G3: 13125
A4: Atinaw, LLC | B4: 44562 | C4: TREO | D4: Nomadx | E4: ARC | F4: $1M | G4: 8925
A5: Duncan & John C Schmidt | B5: 44927 | C5: TREO | D5: Nomadx | E5: ARC | F5: $1M | G5: 2625
A6: LB Business Services | B6: 44930 | C6: TREO | D6: AWAC | E6: ARC | F6: $1M | G6: 1700 | H6: =G6*0.12 -> 204
A7: Laura Fisher (Pisces) | B7: 46027 | C7: Sexual Misconduct | D7: Lloyds | E7: ARC | F7: $1M | G7: 6291 | H7: =G7*12.5% -> 786.375
A8: Laura Fisher (Pisces) | B8: 46027 | C8: EO | D8: Allied Medical | E8: ARC | F8: $3M | G8: 2520 | H8: =G8*12.5% -> 315
A9: Laura Fisher (Pisces) | B9: 46027 | C9: XS EO | D9: Nautilus | E9: ARC | F9: $1M | G9: 9589.97 | H9: =G9*12.5% -> 1198.7462
A10: Laura Fisher (Pisces) | B10: 46027 | C10: XS EO | D10: Hadron | E10: ARC | F10: $2M | G10: 4728.49 | H10: =G10*12.5% -> 591.06125
A11: Investors Preferred | B11: 44942 | C11: FI PKG | D11: Lloyds | E11: RT | F11: $1M | G11: 44127.66 | H11: =G11*11.5% -> 5074.6809
A12: Investors Preferred | B12: 44942 | C12: FI Bond | D12: XL Specialty | E12: ARC | F12: $5M | G12: 8546 | H12: =G12*12.5% -> 1068.25
A13: Hermes Trust Co | B13: 45676 | C13: EO/DO | D13: CNA | E13: ARC | F13: $5M | G13: 48000 | H13: =G13*12.5% -> 6000
A14: Hermes Trust Co | B14: 45676 | C14: FI Bond | D14: CNA | E14: ARC | F14: $4M | G14: 11649 | H14: =G14*12.5% -> 1456.125
A15: Hermes Trust Co | B15: 45676 | C15: Cyber | D15: At Bay | E15: ARC | F15: $2M | G15: 11199.79 | H15: =G15*12.5% -> 1399.9738
A16: City Fields Foundation (Pisces) | B16: 45683 | C16: DO | D16: Scottsdale | E16: ARC | F16: $5M | G16: 4200 | H16: =G16*12.5% -> 525
A17: The Lions Consulting Group | B17: 45684 | C17: TREO | D17: AWAC | E17: ARC | F17: $1M | G17: 1031.75 | H17: =G17*0.125 -> 128.96875
A18: Shock the System | B18: 46049 | C18: DO | D18: Lexington | E18: ARC | F18: $1M | G18: 8886.89 | H18: =G18*0.125 -> 1110.8612
A19: Independent Trustee Alliance/ Kevin Quinn | B19: 44955 | C19: Association Professional | D19: Gemini | E19: ARC | F19: $1M | G19: 1538.74 | H19: =G19*0.125 -> 192.3425
A20: Independent Trustee Alliance/ Kevin Quinn | B20: 44955 | C20: Cyber | D20: At Bay | E20: ARC | F20: $1M | G20: 1048.9 | H20: =G20*0.125 -> 131.1125
A21: Independent Trustee Alliance/ Kevin Quinn | B21: 44955 | C21: D&O | D21: Arch | E21: ARC | F21: $1M | G21: 869 | H21: =G21*12.5% -> 108.625
I22: =SUM(H2:H22) -> 30291.122 | J22: 5975.05 | K22: 99.6
A23: ILS (interactive Legal Services) | B23: 44959 | C23: Cyber | D23: CFC | E23: ARC | F23: $5M | G23: 12000 | H23: =G23*11% -> 1320
A24: ILS (interactive Legal Services) | B24: Feb 2, 2027 | C24: DO | D24: Zurich | E24: ARC | F24: $2M | G24: 3747 | H24: =G24*12% -> 449.64
A25: EBOR (WSG(PTC)) | B25: Feb 2 | C25: Private Trust Co | D25: Travelers | E25: RT | F25: $5M | G25: 106777 | H25: =G25*12% -> 12813.24
A26: Lakeside Accounting Solutions, LLC | B26: 45693 | C26: EO | D26: Houston Casualty | E26: ARC | F26: $1M | G26: 1856 | H26: =G26*12.5% -> 232
A27: South Dakota Trust Association | B27: 44964 | C27: D&O | D27: Travelers | E27: ARC | F27: $1M | G27: 1775 | H27: =G27*12.5% -> 221.875
A28: Center of the Golden One | B28: 46073 | C28: Cyber | D28: CFC | E28: ARC | F28: $1M | G28: 1295 | H28: =G28*12.5% -> 161.875
A29: TEFAF | B29: 45342 | C29: GL/Spectator Accident | D29: HCC | E29: ProSight | F29: $5M | G29: 6313 | H29: =G29*0.1 -> 631.3
A30: TEFAF | B30: 46073 | C30: Exhibitor | D30: HCC | E30: K&K | F30: TBD
A31: TEFAF | B31: 46073 | C31: Event Cancellation | D31: HCC | E31: Affinity | F31: 7761000 | G31: 45706 | H31: 6855.9
A32: TEFAF | B32: 45708 | C32: Fee | H32: 5000
A33: Chandler Trust | B33: 45344 | C33: EO/DO | D33: Texas Insurance Co | E33: ARC | F33: $2.5M | G33: 142500 | H33: =G33*0.125 -> 17812.5
A34: Chandler Trust | B34: 45344 | C34: EO/DO | D34: Crum & Forster | E34: ARC | F34: $2.5M | G34: 71250 | H34: =G34*0.125 -> 8906.25
A35: Chandler Trust | B35: 45344 | C35: EO/DO | D35: Coaction | E35: ARC | F35: $5M | G35: 95562 | H35: =G35*0.125 -> 11945.25
A36: Chandler Trust | B36: 45344 | C36: EO/DO | D36: XL Specialty | E36: ARC | F36: $5M | G36: 67500 | H36: =G36*0.125 -> 8437.5
A37: Chandler Trust | B37: 45344 | C37: EO/DO | D37: Convex | E37: ARC | F37: $5M | G37: 50250 | H37: =G37*0.125 -> 6281.25
A38: Chandler Trust | B38: 45344 | C38: EO/DO | D38: Hanover Insurance Company | E38: ARC | F38: $5M | G38: 40199.06 | H38: =G38*0.125 -> 5024.8825
A39: Chandler Trust | B39: 45344 | C39: EO/DO | D39: CNA | E39: ARC | F39: $5M | G39: 33772 | H39: =G39*0.125 -> 4221.5
A40: Chandler Trust | B40: 45344 | C40: EO/DO | D40: Ascot | E40: ARC | F40: $5M/$20M | G40: 26250 | H40: =G40*0.125 -> 3281.25
A41: Chandler Trust | B41: 45344 | C41: EO/DO | D41: Aegis | E41: ARC | F41: $5M/$20M | G41: 26250 | H41: =G41*0.125 -> 3281.25
A42: Chandler Trust | B42: 45344 | C42: EO/DO | D42: AWAC | E42: ARC | F42: $5M/$20M | G42: 26250 | H42: =G42*0.125 -> 3281.25
A43: Chandler Trust | B43: 45344 | C43: EO/DO | D43: Amtrust | E43: ARC | F43: $5M/$20M | G43: 26250 | H43: =G43*0.125 -> 3281.25
A44: Fortius Metals Inc | B44: 44979 | C44: Property | D44: Scottsdale | E44: CRC | F44: On schedule | G44: 8922.57 | H44: =G44*10% -> 892.257
A45: Fortius Metals Inc | B45: 44979 | C45: XS | D45: Admiral | E45: CRC | F45: $1M xs | G45: 7046 | H45: =G45*10% -> 704.6
A46: Fortius Metals Inc | B46: 44979 | C46: GL | D46: Kinsale | E46: CRC | F46: $1M/$2M | G46: 23677 | H46: =G46*10% -> 2367.7
A47: Fortius Metals Inc | B47: 44979 | C47: D&O | D47: Admiral | E47: ARC | F47: $1M | G47: 7734 | H47: =G47*10% -> 773.4
A48: Carola PTC LLC | B48: 46076 | C48: FI Bond | E48: ARC | F48: $1M | G48: 7500 | H48: =G48*0.125 -> 937.5
A49: Carola PTC LLC | B49: 46076 | C49: Cyber | D49: At Bay | E49: ARC | F49: $1M | G49: 700 | H49: =G49*0.125 -> 87.5
A50: Carola PTC LLC | B50: 46076 | C50: Cyber 1st XS | D50: Erisk | E50: ARC | F50: $1M | G50: 1000 | H50: =G50*0.125 -> 125
A51: Carola PTC LLC | B51: 46076 | C51: Cyber 2nd XS | D51: Corvus | E51: ARC | F51: $1M | G51: 1000 | H51: =G51*0.125 -> 125
A52: Carola PTC LLC | B52: 46076 | C52: Cyber 3rd XS | D52: Intact | E52: ARC | F52: $1M | G52: 8000 | H52: =G52*0.125 -> 1000
A53: James Blakey | B53: 45708 | C53: TREO | D53: Nomadx | E53: ARC | F53: $1M | G53: 3117
A54: Marshall Lee Stocker | B54: 45348 | C54: TREO | D54: Nomadx | E54: ARC | F54: $3M | G54: 17719
I55: =SUM(H23:H55) -> 110452.92 | J55: 4771.14
A56: WE Trust | B56: 44986 | C56: TREO | D56: Nomadx | E56: ARC | F56: $2M | G56: 37057
A57: WE Trust | B57: 44986 | C57: DO/EPL | D57: Erisk | E57: ARC | F57: $2M DO $1M EPL | G57: 7150 | H57: =G57*12.5% -> 893.75
A58: WE Trust | B58: 44986 | C58: FI Bond | D58: AXA XL | E58: ARC | F58: $1M | G58: 7570 | H58: =G58*10% -> 757
A59: WE Trust | B59: 44986 | C59: Cyber | D59: CFC | E59: ARC | F59: $2M | G59: 3590 | H59: 448.75
A60: WE Trust | B60: 46082 | C60: BOP | D60: Hartford | E60: Element | F60: $1M | G60: 1758 | H60: =G60*0.1 -> 175.8
A61: Lotus Fiduciary | B61: 45717 | C61: TREO | D61: Allied World | E61: ARC | F61: $3M | G61: 10460 | H61: =G61*0.125 -> 1307.5
A62: Lotus Fiduciary | B62: 46082 | C62: DO/EPL | D62: Templar | E62: ARC | F62: $1M | G62: 6750 | H62: =G62*0.125 -> 843.75
A63: Lotus Fiduciary | B63: 46082 | C63: Cyber | D63: At-Bay | E63: ARC | F63: $1M | G63: 1216 | H63: =G63*0.125 -> 152
A64: Lotus Fiduciary | B64: 46082 | C64: Cyber 1st | D64: CNA | E64: ARC | F64: $1M x $1M | G64: 1025 | H64: =G64*0.125 -> 128.125
A65: Lotus Fiduciary | B65: 46082 | C65: Cyber 2nd | D65: Erisk | E65: ARC | F65: $1M x $2M | G65: 1000 | H65: =G65*0.125 -> 125
A66: Lotus Fiduciary | B66: 46082 | C66: Cyber 3rd | D66: Intact | E66: ARC | F66: $700K SE | G66: 8000 | H66: =G66*0.125 -> 1000
A67: Lotus Fiduciary | B67: 46082 | C67: BOP | D67: Hartford | E67: Element | F67: $1M | G67: 1214 | H67: =G67*0.1 -> 121.4
A68: Barry Thomashow | B68: 45358 | C68: TREO | D68: Chubb | E68: ARC | F68: $1M | G68: 1989 | H68: =G68*0.125 -> 248.625
A69: Westerman Foundation | B69: 45723 | C69: DO EPL | D69: AIG | E69: ARC | F69: $1M | G69: 3114 | H69: =G69*0.125 -> 389.25
A70: Ranya Kahtan | B70: 46090 | C70: TREO | D70: Lloyds (Hiscox) | E70: ARC | F70: $2M | G70: 5780 | H70: 722.5
A71: Clermont Trust USA LLC | B71: 45727 | C71: DO/EO | D71: QBE | E71: ARC | F71: $1M | G71: 16000 | H71: =G71*0.125 -> 2000
A72: Clermont Trust USA LLC | B72: 45727 | C72: Cyber | D72: At Bay | E72: ARC | F72: $1M | G72: 1091 | H72: =G72*0.125 -> 136.375
A73: Clermont Trust USA LLC | B73: 45727 | C73: FIB | D73: AIG | E73: ARC | F73: $1M | G73: 3582 | H73: =G73*0.125 -> 447.75
A74: Dakota Hill (PTC) | B74: 44999 | C74: TREO | D74: Nomadx | E74: ARC | F74: $1M | G74: 20992
A75: James Carey Nord | B75: 45002 | C75: TREO | D75: Siriuspoint Specialty | E75: ARC | F75: $2M | G75: 15000 | H75: =G75*12.5% -> 1875
A76: Ascent Management LLC | B76: 45736 | C76: EO DO Package | D76: Crum & Forster | E76: ARC | F76: $2.5M | G76: 39220 | H76: =G76*12.5% -> 4902.5
A77: Ascent Management LLC | B77: 45736 | C77: XS DO EO | D77: CNA | E77: ARC | F77: $2.5M | G77: 21860 | H77: =G77*12.5% -> 2732.5
A78: Ascent Management LLC | B78: 46101 | C78: Cyber | D78: At-Bay | E78: ARC | F78: $1M | G78: 2995 | H78: =G78*12.5% -> 374.375
A79: Ascent Management LLC | B79: 46101 | C79: XS Cyber | D79: Westchester | E79: ARC | F79: $1M | G79: 1960 | H79: =G79*12.5% -> 245
A80: Ascent Management LLC | B80: 46101 | C80: XS Cyber | D80: E-Risk | E80: ARC | F80: $1M | G80: 2241 | H80: =G80*12.5% -> 280.125
A81: Ascent Management LLC | B81: 46101 | C81: FI Bond | D81: AIG | E81: ARC | F81: $1M | G81: 6209 | H81: =G81*12.5% -> 776.125
A82: Saul Costa | B82: 45737 | C82: Agency Fee | H82: 5000
A83: Center of the Golden One | B83: 45737 | C83: Agency Fee | H83: 3000
I84: =SUM(H56:H84) -> 29083.2 | J84: 2428.13 | K84: 4853.85
A85: Mark Seski | B85: 46113 | C85: TREO | D85: Nomadx | E85: ARC | F85: $1M | G85: 3125
A86: Northway Wealth Advisors | B86: 45750 | C86: TREO | D86: Nomadx | E86: ARC | F86: $1M | G86: 2500
A87: Gideon Rothschild | B87: 45385 | C87: TREO | D87: Nomadx | E87: ARC | F87: $1M | G87: 3265
A88: Charles River | B88: 46115 | C88: DO EO | D88: Hanover | E88: ARC | F88: $2.5M | G88: 13521 | H88: =G88*12.5% -> 1690.125
A89: Charles River | B89: 46115 | C89: Cyber | D89: At-Bay | E89: ARC | F89: $1M | G89: 700 | H89: =G89*12.5% -> 87.5
A90: Charles River | B90: 46115 | C90: Cyber 1st XS | D90: Scottsdale | E90: ARC | F90: $1M | G90: 1000 | H90: 125
A91: Charles River | B91: 46115 | C91: Cyber 2nd XS | D91: CNA | E91: ARC | F91: $1M | G91: 1000 | H91: =G91*12.5% -> 125
A92: 1248 Trust Company | B92: 45751 | C92: FI Bond | D92: Federal Ins co | E92: ARC | F92: 1M | G92: 6877 | H92: =G92*12.5% -> 859.625
A93: 1248 Trust Company | B93: 45386 | C93: DO EO | D93: Crum & Forster | E93: ARC | F93: $2.5M | G93: 35625 | H93: =G93*12.5% -> 4453.125
A94: 1248 Trust Company | B94: 45386 | C94: XS DO EO | D94: Euclid | E94: ARC | F94: $2.5M | G94: 25638 | H94: =G94*12.5% -> 3204.75
A95: Matthew Hoy | B95: 45398 | C95: TREO | D95: Hiscox | E95: ARC | F95: $5M | G95: 16949 | H95: =G95*12.5% -> 2118.625
A96: Center of the Golden One | B96: 45764 | C96: EO | D96: RSUI | E96: ARC | F96: $1M | G96: 12000 | H96: =G96*12.5% -> 1500
A97: Manton Foundation | B97: 45768 | C97: DO /EPL | D97: Everest | E97: ARC | F97: $3M | G97: 4711 | H97: 588.88
A98: Manton Foundation | B98: 45768 | C98: EO | D98: Huntersure | E98: ARC | F98: $2.5M | G98: 11615 | H98: =G98*12.5% -> 1451.875
A99: Manton Foundation | B99: 45768 | C99: Cyber | D99: At-Bay | E99: ARC | F99: $1M | G99: 4454 | H99: =G99*12.5% -> 556.75
A100: Manton Foundation | B100: 45768 | C100: XS Cyber | D100: CNA | E100: ARC | F100: $1M | G100: 3158 | H100: =G100*12.5% -> 394.75
...

Sheet Employee Roster
B1: Project Rocky - Employee Roster
F3: Book of | H3: Reported | L3: Seller Pro Forma | P3: MMA Pro Forma | U3: Variance | W3: Variance | Y3: Social | AA3: Payroll
C4: $ | D4: Name | E4: Title | F4: Business | H4: Base | I4: Comm. | J4: Bonus | K4: Total | L4: Base | M4: Comm. | N4: Bonus | O4: Total | P4: Base | Q4: Comm. | R4: Bonus | S4: Total | U4: to Reported | W4: to Seller PF | Y4: Security | Z4: Medicare | AA4: Taxes | AB4: 401(k) | AC4: Medical
C6: 1 | D6: Judy Pearson | E6: Principal | F6: ='Pro Forma Financials'!H16 -> 591831.71 | H6: 200000 | I6: 0 | J6: 0 | K6: =SUM(H6:J6) -> 200000 | L6: 0 | M6: 0 | N6: 0 | O6: =SUM(L6:N6) -> 0 | P6: 200000 | R6: =P6*25% -> 50000 | S6: =SUM(P6:R6) -> 250000 | U6: =S6-K6 -> 50000 | W6: =+S6-O6 -> 250000 | Y6: =$AC$34*MIN($S6,$AC$33) -> 11439 | Z6: =$AC$37*$S6 -> 3625 | AA6: =SUM(Y6:Z6) -> 15064 | AB6: =$AC$41*MIN(P6+Q6,$AC$40) -> 8000 | AC6: =IF($S6>0,IF($S$49=1,$S$46,$S$44),0) -> 11600
D7: Unreconciled variance | F7: 0 | H7: 0 | I7: 0 | J7: 0 | L7: 0 | M7: 0 | N7: 0 | O7: =SUM(L7:N7) -> 0 | P7: 0 | Q7: 0 | R7: 0 | S7: =SUM(P7:R7) -> 0 | U7: =S7-K7 -> 0 | W7: =+S7-O7 -> 0 | Z7: =$AC$37*$S7 -> 0 | AA7: =SUM(Y7:Z7) -> 0
C8: Total Shareholders | F8: =SUM(F6:F7) -> 591831.71 | H8: =SUM(H6:H7) -> 200000 | I8: =SUM(I6:I7) -> 0 | J8: =SUM(J6:J7) -> 0 | K8: =SUM(K6:K7) -> 200000 | L8: =SUM(L6:L7) -> 0 | M8: =SUM(M6:M7) -> 0 | N8: =SUM(N6:N7) -> 0 | O8: =SUM(O6:O7) -> 0 | ... S8: =SUM(S6:S7) -> 250000 | U8: =SUM(U6:U7) -> 50000 | W8: =SUM(W6:W7) -> 250000 | Y8: =SUM(Y6:Y7) -> 11439 | Z8: =SUM(Z6:Z7) -> 3625 | AA8: =SUM(AA6:AA7) -> 15064 | AB8: =SUM(AB6:AB7) -> 8000 | AC8: =SUM(AC6:AC7) -> 11600
C10: =MAX($C$6:$C9)+1 -> 2 | F10: 0 | H10: 0 | I10: 0 | J10: 0 | K10: =SUM(H10:J10) -> 0 | L10: 0 | M10: 0 | N10: 0 | O10: =SUM(L10:N10) -> 0 | P10: 0 | Q10: 0 | R10: 0 | S10: =SUM(P10:R10) -> 0 | U10: =S10-K10 -> 0 | W10: =+S10-O10 -> 0 | Y10: =$AC$34*MIN($S10,$AC$33) -> 0 | Z10: =$AC$37*$S10 -> 0 | AA10: =SUM(Y10:Z10) -> 0 | AB10: =$AC$41*MIN(P10+Q10,$AC$40) -> 0 | AC10: =IF($S10>0,IF($S$49=1,$S$46,$S$44),0) -> 0
C11: =MAX($C$6:$C10)+1 -> 3 | F11: 0 | H11: 0 | I11: 0 | J11: 0 | K11: =SUM(H11:J11) -> 0 | L11: 0 | M11: 0 | N11: 0 | O11: =SUM(L11:N11) -> 0 | P11: 0 | Q11: 0 | R11: 0 | S11: =SUM(P11:R11) -> 0 | U11: =S11-K11 -> 0 | W11: =+S11-O11 -> 0 | Y11: =$AC$34*MIN($S11,$AC$33) -> 0 | Z11: =$AC$37*$S11 -> 0 | AA11: =SUM(Y11:Z11) -> 0 | AB11: =$AC$41*MIN(P11+Q11,$AC$40) -> 0 | AC11: =IF($S11>0,IF($S$49=1,$S$46,$S$44),0) -> 0
C12: =MAX($C$6:$C11)+1 -> 4 | F12: 0 | H12: 0 | I12: 0 | J12: 0 | K12: =SUM(H12:J12) -> 0 | L12: 0 | M12: 0 | N12: 0 | O12: =SUM(L12:N12) -> 0 | P12: 0 | Q12: 0 | R12: 0 | S12: =SUM(P12:R12) -> 0 | U12: =S12-K12 -> 0 | W12: =+S12-O12 -> 0 | Y12: =$AC$34*MIN($S12,$AC$33) -> 0 | Z12: =$AC$37*$S12 -> 0 | AA12: =SUM(Y12:Z12) -> 0 | AB12: =$AC$41*MIN(P12+Q12,$AC$40) -> 0 | AC12: =IF($S12>0,IF($S$49=1,$S$46,$S$44),0) -> 0
C13: =MAX($C$6:$C12)+1 -> 5 | F13: 0 | H13: 0 | I13: 0 | J13: 0 | K13: =SUM(H13:J13) -> 0 | L13: 0 | M13: 0 | N13: 0 | O13: =SUM(L13:N13) -> 0 | P13: 0 | Q13: 0 | R13: 0 | S13: =SUM(P13:R13) -> 0 | U13: =S13-K13 -> 0 | W13: =+S13-O13 -> 0 | Y13: =$AC$34*MIN($S13,$AC$33) -> 0 | Z13: =$AC$37*$S13 -> 0 | AA13: =SUM(Y13:Z13) -> 0 | AB13: =$AC$41*MIN(P13+Q13,$AC$40) -> 0 | AC13: =IF($S13>0,IF($S$49=1,$S$46,$S$44),0) -> 0
D14: Unreconciled variance | F14: 0 | H14: 0 | I14: 0 | J14: 0 | K14: =[1]PF_Schedule!G58-SUM('Employee Roster'!K10:K13) -> 0 | L14: 0 | M14: 0 | N14: 0 | O14: =SUM(L14:N14) -> 0 | P14: 0 | Q14: 0 | R14: 0 | S14: =SUM(P14:R14) -> 0 | U14: =S14-K14 -> 0 | W14: =+S14-O14 -> 0
C15: Total Non-Shareholder Producers | F15: =SUM(F10:F14) -> 0 | H15: =SUM(H10:H14) -> 0 | I15: =SUM(I10:I14) -> 0 | J15: =SUM(J10:J14) -> 0 | K15: =SUM(K10:K14) -> 0 | L15: =SUM(L10:L14) -> 0 | M15: =SUM(M10:M14) -> 0 | N15: =SUM(N10:N14) -> 0 | O15: =SUM(O10:O14) -> 0 | ... S15: =SUM(S10:S14) -> 0 | U15: =SUM(U10:U14) -> 0 | W15: =SUM(W10:W14) -> 0 | Y15: =SUM(Y10:Y14) -> 0 | Z15: =SUM(Z10:Z14) -> 0 | AA15: =SUM(AA10:AA14) -> 0 | AB15: =SUM(AB10:AB14) -> 0 | AC15: =SUM(AC10:AC14) -> 0
C17: 2 | D17: Alex Gruitch | E17: Associate AM | F17: 0 | H17: 60000 | I17: 0 | J17: 0 | K17: =SUM(H17:J17) -> 60000 | L17: 0 | M17: 0 | N17: 0 | O17: =SUM(L17:N17) -> 0 | P17: =+H17 -> 60000 | Q17: 0 | R17: =+P17*0.05 -> 3000 | S17: =SUM(P17:R17) -> 63000 | U17: =S17-K17 -> 3000 | W17: =+S17-O17 -> 63000 | Y17: =$AC$34*MIN($S17,$AC$33) -> 3906 | Z17: =$AC$37*$S17 -> 913.5 | AA17: =SUM(Y17:Z17) -> 4819.5 | AB17: =$AC$41*MIN(P17+Q17,$AC$40) -> 2400 | AC17: =IF($S17>0,IF($S$49=1,$S$46,$S$44),0) -> 11600
C18: 3 | D18: Replacement hire for Liam Franks | E18: Associate AM | F18: 0 | H18: 45000 | I18: 0 | J18: 0 | K18: =SUM(H18:J18) -> 45000 | L18: 0 | M18: 0 | N18: 0 | O18: =SUM(L18:N18) -> 0 | P18: =H18 -> 45000 | Q18: 0 | R18: =+P18*0.05 -> 2250 | S18: =SUM(P18:R18) -> 47250 | U18: =S18-K18 -> 2250 | W18: =+S18-O18 -> 47250 | Y18: =$AC$34*MIN($S18,$AC$33) -> 2929.5 | Z18: =$AC$37*$S18 -> 685.125 | AA18: =SUM(Y18:Z18) -> 3614.625 | AB18: =$AC$41*MIN(P18+Q18,$AC$40) -> 1800 | AC18: =IF($S18>0,IF($S$49=1,$S$46,$S$44),0) -> 11600
C19: =MAX($C$6:$C18)+1 -> 6 | F19: 0 | H19: 0 | I19: 0 | J19: 0 | K19: =SUM(H19:J19) -> 0 | L19: 0 | M19: 0 | N19: 0 | O19: =SUM(L19:N19) -> 0 | P19: 0 | Q19: 0 | R19: 0 | S19: =SUM(P19:R19) -> 0 | U19: =S19-K19 -> 0 | W19: =+S19-O19 -> 0 | Y19: =$AC$34*MIN($S19,$AC$33) -> 0 | Z19: =$AC$37*$S19 -> 0 | AA19: =SUM(Y19:Z19) -> 0 | AB19: =$AC$41*MIN(P19+Q19,$AC$40) -> 0 | AC19: =IF($S19>0,IF($S$49=1,$S$46,$S$44),0) -> 0
C20: =MAX($C$6:$C19)+1 -> 7 | F20: 0 | H20: 0 | I20: 0 | J20: 0 | K20: =SUM(H20:J20) -> 0 | L20: 0 | M20: 0 | N20: 0 | O20: =SUM(L20:N20) -> 0 | P20: 0 | Q20: 0 | R20: 0 | S20: =SUM(P20:R20) -> 0 | U20: =S20-K20 -> 0 | W20: =+S20-O20 -> 0 | Y20: =$AC$34*MIN($S20,$AC$33) -> 0 | Z20: =$AC$37*$S20 -> 0 | AA20: =SUM(Y20:Z20) -> 0 | AB20: =$AC$41*MIN(P20+Q20,$AC$40) -> 0 | AC20: =IF($S20>0,IF($S$49=1,$S$46,$S$44),0) -> 0
C21: =MAX($C$6:$C20)+1 -> 8 | F21: 0 | H21: 0 | I21: 0 | J21: 0 | K21: =SUM(H21:J21) -> 0 | L21: 0 | M21: 0 | N21: 0 | O21: =SUM(L21:N21) -> 0 | P21: 0 | Q21: 0 | R21: 0 | S21: =SUM(P21:R21) -> 0 | U21: =S21-K21 -> 0 | W21: =+S21-O21 -> 0 | Y21: =$AC$34*MIN($S21,$AC$33) -> 0 | Z21: =$AC$37*$S21 -> 0 | AA21: =SUM(Y21:Z21) -> 0 | AB21: =$AC$41*MIN(P21+Q21,$AC$40) -> 0 | AC21: =IF($S21>0,IF($S$49=1,$S$46,$S$44),0) -> 0
C22: =MAX($C$6:$C21)+1 -> 9 | E22: Terminated | F22: 0 | H22: 0 | I22: 0 | J22: 0 | K22: =SUM(H22:J22) -> 0 | L22: 0 | M22: 0 | N22: 0 | O22: =SUM(L22:N22) -> 0 | P22: 0 | Q22: 0 | R22: 0 | S22: =SUM(P22:R22) -> 0 | U22: =S22-K22 -> 0 | W22: =+S22-O22 -> 0 | Y22: =$AC$34*MIN($S22,$AC$33) -> 0 | Z22: =$AC$37*$S22 -> 0 | AA22: =SUM(Y22:Z22) -> 0 | AB22: =$AC$41*MIN(P22+Q22,$AC$40) -> 0 | AC22: =IF($S22>0,IF($S$49=1,$S$46,$S$44),0) -> 0
D23: Unreconciled difference to P&L | F23: 0 | H23: 0 | I23: 0 | J23: 0 | L23: 0 | M23: 0 | N23: 0 | O23: =SUM(L23:N23) -> 0 | P23: 0 | Q23: 0 | R23: 0 | S23: =SUM(P23:R23) -> 0 | U23: =S23-K23 -> 0 | W23: =+S23-O23 -> 0
C24: Total Staff & Support | F24: =SUM(F17:F23) -> 0 | H24: =SUM(H17:H23) -> 105000 | I24: =SUM(I17:I23) -> 0 | J24: =SUM(J17:J23) -> 0 | K24: =SUM(K17:K23) -> 105000 | L24: =SUM(L17:L23) -> 0 | M24: =SUM(M17:M23) -> 0 | N24: =SUM(N17:N23) -> 0 | O24: =SUM(O17:O23) -> 0 | ... S24: =SUM(S17:S23) -> 110250 | U24: =SUM(U17:U23) -> 5250 | W24: =SUM(W17:W23) -> 110250 | Y24: =SUM(Y17:Y23) -> 6835.5 | Z24: =SUM(Z17:Z23) -> 1598.625 | AA24: =SUM(AA17:AA23) -> 8434.125 | AB24: =SUM(AB17:AB23) -> 4200 | AC24: =SUM(AC17:AC23) -> 23200
C26: Total Compensation | F26: =F8+F15+F24 -> 591831.71 | H26: =H8+H15+H24 -> 305000 | I26: =I8+I15+I24 -> 0 | J26: =J8+J15+J24 -> 0 | K26: =K8+K15+K24 -> 305000 | L26: =L8+L15+L24 -> 0 | M26: =M8+M15+M24 -> 0 | N26: =N8+N15+N24 -> 0 | O26: =O8+O15+O24 -> 0 | ... S26: =S8+S15+S24 -> 360250 | U26: =U8+U15+U24 -> 55250 | W26: =W8+W15+W24 -> 360250 | Y26: =Y8+Y15+Y24 -> 18274.5 | Z26: =Z8+Z15+Z24 -> 5223.625 | AA26: =AA8+AA15+AA24 -> 23498.125 | AB26: =AB8+AB15+AB24 -> 12200 | AC26: =AC8+AC15+AC24 -> 34800
C28: Per Source | F28: ='Pro Forma Financials'!H11 -> 591831.71 | K28: ='Pro Forma Financials'!C40 -> 308250.3 | S28: =S26 -> 360250 | AA28: ='Pro Forma Financials'!H49 -> 23498.125 | AB28: ='Pro Forma Financials'!H54 -> 12200 | AC28: ='Pro Forma Financials'!H44 -> 34800
C29: Variance | F29: =+F26-F28 -> 0 | K29: =+K26-K28 -> -3250.3 | O29: =+O26-O28 -> 0 | S29: =+S26-S28 -> 0 | AA29: =+AA26-AA28 -> 0 | AB29: =+AB26-AB28 -> 0 | AC29: =+AC26-AC28 -> 0
P31: Commission Assumptions | Y31: Benefit Assumptions
P32: Book Split | Y32: Social Security
P33: Growth Business | S33: 0.1 | Y33: Income Limit | AC33: 184500
P34: Base Business | S34: 0.9 | Y34: Social Security Tax Rate | AC34: 0.062
P36: Commission Structure | Y36: Medicare
P37: Commission on Growth | S37: 0.4 | Y37: Medicare Tax Rate | AC37: 0.0145
P38: Commission on Base | S38: 0.25
P39: Assumed Commission Percentage | S39: =SUMPRODUCT(S33:S34,S37:S38) -> 0.265 | Y39: 401(k)
Y40: Income Limit | AC40: 360000
P41: Benefits comparison | Y41: MMA Match Rate | AC41: =8%*0.5 -> 0.04
P42: Reported | S42: =[1]PF_Schedule!G70 -> 0
P43: Number of EEs | S43: =MAX(C6:C24) -> 9 | Y43: Medical
P44: Per EE | S44: =S42/S43 -> 0 | Y44: Cost per Employee | AC44: =ROUND(VLOOKUP([1]Inputs!H14,'[1]Benefit Cost by Region'!$A$20:$D$31,4,FALSE),-2) -> 11600
P46: MMA Region | S46: =ROUND(VLOOKUP([1]Inputs!H14,'[1]Benefit Cost by Region'!$A$20:$D$31,4,FALSE),-2) -> 11600 | Y46: Staff Bonus
P47: Variance | S47: =S44-S46 -> -11600 | Y47: Bonus per Employee | AC47: 0.03
P49: Benefits Toggle (1 = MMA plan) | S49: 1

Sheet June-26 TTM 
A1: Project Rocky
A2: Income Statement
B5: June 2026 TTM
A6: Income
A7: Sales | B7: 569203.54
A8: Total for Income | B8: =B6+B7 -> 569203.54
A9: Gross Profit | B9: =B8-0 -> 569203.54
A10: Expenses
A11: Advertising & marketing | B11: 510.76
A12: Business licenses | B12: 1871.7
A13: Dues and Memberships | B13: 6147
A14: Employee benefits | B14: 4150
A15: Employee Expense Reimbursement | B15: 457.72
A16: General business expenses | B16: 14.35
A17: Bank fees & service charges | B17: 242.16
A18: Continuing education | B18: 7652.27
A19: Memberships & subscriptions | B19: 99
A20: Total for General business expenses | B20: =B16+B17+B18+B19 -> 8007.78
A21: Insurance | B21: 9381.85
A22: Legal & accounting services | B22: 97.85
A23: Accounting fees | B23: 4007.78
A24: Legal fees | B24: 5295.51
A25: Total for Legal & accounting services | B25: =B22+B23+B24 -> 9401.14
A26: Meals | B26: 5098
A27: Meals with clients | B27: 18.05
A28: Total for Meals | B28: =B26+B27 -> 5116.05
A29: Office expenses | B29: 340.42
A30: Office supplies | B30: 3389.49
A31: Shipping & postage | B31: 233.61
A32: Software, IT & apps | B32: 24553.15
A33: Total for Office expenses | B33: =B29+B30+B31+B32 -> 28516.67
A34: Payroll expenses
A35: Officers Salary | B35: 183335.48
A36: Payroll Fees | B36: 1047.1
A37: Payroll taxes (Company) | B37: 23961.38
A38: Staff Wages | B38: 124914.82
A39: Total for Payroll expenses | B39: =B34+B35+B36+B37+B38 -> 333258.78
A40: Professional Services | B40: 2705.8
A41: Rent | B41: 5882.4
A42: OFF RENT | B42: 239.88
A43: Total for Rent | B43: =B41+B42 -> 6122.28
A44: Travel | B44: 791.78
A45: Airfare | B45: 14971.31
A46: Hotels | B46: 5567.91
A47: Taxis or shared rides | B47: 2018.49
A48: Total for Travel | B48: =B44+B45+B46+B47 -> 23349.49
A49: Total for Expenses | B49: 438997.02
A50: Net Operating Income | B50: =B9-B49 -> 130206.52
A51: Other Income
A52: Convenience Fee Income | B52: 205
A53: Total for Other Income | B53: =B51+B52 -> 205
A54: Other Expenses
A55: Vehicle expenses
A56: Parking & tolls | B56: 175
A57: Vehicle gas & fuel | B57: 52.15
A58: Total for Vehicle expenses | B58: =B55+B56+B57 -> 227.15
A59: Total for Other Expenses | B59: =B54+B58 -> 227.15
A60: Net Other Income | B60: =B53-B59 -> -22.15
A61: Net Income | B61: =B50+B60 -> 130184.37
A67: Accrual Basis Monday, August 03, 2026 09:57 AM GMT-04:00

Sheet 2024 BS
A1: Precision Brokers, LLC
A2: Balance Sheet
A3: As of Dec 31, 2024
B5: Total
A6: Assets
A7: Current Assets
A8: Bank Accounts
A9: Chase Business Operating 2157 | B9: 32280.77
A10: Chase Premium 5805 | B10: 98960.65
A11: Total for Bank Accounts | B11: =B8+B9+B10 -> 131241.42
A12: Accounts Receivable
A13: Accounts Receivable (A/R) | B13: 30476.74
A14: Total for Accounts Receivable | B14: =B12+B13 -> 30476.74
A15: Total for Current Assets | B15: =B7+B11+B14 -> 161718.16
A16: Total for Assets | B16: =B6+B15 -> 161718.16
A17: Liabilities and Equity
A18: Liabilities
A19: Current Liabilities
A20: Credit Cards
A21: Chase - Brudnicki 8695 | B21: 0
A22: Chase Credit Card - United 8687 | B22: 4021.45
A23: Total for Credit Cards | B23: =B20+B21+B22 -> 4021.45
A24: Other Current Liabilities
A25: Commissions Due to Precision | B25: -45847.39
A26: Insurance Premiums Owed | B26: 175314.78
A27: Total for Other Current Liabilities | B27: =B24+B25+B26 -> 129467.39
A28: Total for Current Liabilities | B28: =B19+B23+B27 -> 133488.84
A29: Total for Liabilities | B29: =B18+B28 -> 133488.84
A30: Equity
A31: Opening balance equity | B31: 0
A32: Retained Earnings
A33: Net Income | B33: 28229.32
A34: Total for Equity | B34: =B30+B31+B32+B33 -> 28229.32
A35: Total for Liabilities and Equity | B35: =B17+B29+B34 -> 161718.16
A37: Footnote: Precision Brokers’ balance sheet reflects both client premiums receivable and premiums payable to carriers. The portion of premiums representing commissions due to Precision is recorded as an offset against the carrier liability, reducing the total payable balance. Revenue is recognized when commissions are swept from the premium trust account to the operating account, at which point the income statement reflects earned commissions.
A39: Accrual Basis Wednesday, July 29, 2026 11:36 AM GMT-06:00

Sheet 2025 BS
A1: Precision Brokers, LLC
A2: Balance Sheet
A3: As of Dec 31, 2025
B5: Total
A6: Assets
A7: Current Assets
A8: Bank Accounts
A9: Chase Business Operating 2157 | B9: 27489.49
A10: Chase Premium 5805 | B10: 248798.66
A11: Operating Cash (Trust Restricted) | B11: 13293.71
A12: Operating Cash (Unrestricted) | B12: -13293.71
A13: Total for Bank Accounts | B13: =B8+B9+B10+B11+B12 -> 276288.15
A14: Accounts Receivable
A15: Accounts Receivable (A/R) | B15: 244788.89
A16: Total for Accounts Receivable | B16: =B14+B15 -> 244788.89
A17: Other Current Assets
A18: Payments to deposit | B18: 0
A19: Total for Other Current Assets | B19: =B17+B18 -> 0
A20: Total for Current Assets | B20: =B7+B13+B16+B19 -> 521077.04
A21: Fixed Assets
A22: Computer and Hardware | B22: 2233.7
A23: Total for Fixed Assets | B23: =B21+B22 -> 2233.7
A24: Other Assets
A25: Security deposits | B25: 5546.04
A26: Total for Other Assets | B26: =B24+B25 -> 5546.04
A27: Total for Assets | B27: =B6+B20+B23+B26 -> 528856.78
A28: Liabilities and Equity
A29: Liabilities
A30: Current Liabilities
A31: Credit Cards
A32: Chase - Brudnicki 8695 | B32: 0
A33: Chase Credit Card - United 8687 | B33: 49.42
A34: Total for Credit Cards | B34: =B31+B32+B33 -> 49.42
A35: Other Current Liabilities
A36: Commissions Due to Precision | B36: -281589.91
A37: Insurance Premiums Owed | B37: 788471.17
A38: Total for Other Current Liabilities | B38: =B35+B36+B37 -> 506881.26
A39: Total for Current Liabilities | B39: =B30+B34+B38 -> 506930.68
A40: Total for Liabilities | B40: =B29+B39 -> 506930.68
A41: Equity
A42: Opening balance equity | B42: 0
A43: Partner distributions
A44: Hannah Brudnicki | B44: -3051.63
A45: Total for Partner distributions | B45: =B43+B44 -> -3051.63
A46: Retained Earnings | B46: 28229.32
A47: Net Income | B47: -3251.59
A48: Total for Equity | B48: =B41+B42+B45+B46+B47 -> 21926.1
A49: Total for Liabilities and Equity | B49: =B28+B40+B48 -> 528856.78
A51: Footnote: Precision Brokers’ balance sheet reflects both client premiums receivable and premiums payable to carriers. The portion of premiums representing commissions due to Precision is recorded as an offset against the carrier liability, reducing the total payable balance. Revenue is recognized when commissions are swept from the premium trust account to the operating account, at which point the income statement reflects earned commissions.
A53: Accrual Basis Wednesday, July 29, 2026 11:35 AM GMT-06:00

Sheet Trending Balance Sheet
A1: Project Rocky
A2: Trending Balance Sheet
B5: 2024 | C5: 2025 | D5: As of Jun 30, 2026
A6: Assets
A7: Current Assets
A8: Bank Accounts
A9: Chase Business Operating 2157 | B9: ='2024 BS'!B9 -> 32280.77 | C9: ='2025 BS'!B9 -> 27489.49 | D9: 117004.95
A10: Chase Premium 5805 | B10: ='2024 BS'!B10 -> 98960.65 | C10: ='2025 BS'!B10 -> 248798.66 | D10: 32739.54
A11: Operating Cash (Trust Restricted) | C11: ='2025 BS'!B11 -> 13293.71 | D11: 13293.71
A12: Operating Cash (Unrestricted) | C12: ='2025 BS'!B12 -> -13293.71 | D12: -13293.71
A13: Total for Bank Accounts | B13: =B8+B9+B10+B11+B12 -> 131241.42 | C13: =C8+C9+C10+C11+C12 -> 276288.15 | D13: =D8+D9+D10+D11+D12 -> 149744.49
A14: Accounts Receivable
A15: Accounts Receivable (A/R) | B15: ='2024 BS'!B13 -> 30476.74 | C15: ='2025 BS'!B15 -> 244788.89 | D15: 25944.12
A16: Total for Accounts Receivable | B16: =B14+B15 -> 30476.74 | C16: =C14+C15 -> 244788.89 | D16: =D14+D15 -> 25944.12
A17: Other Current Assets
A18: Payments to deposit | C18: ='2025 BS'!B18 -> 0 | D18: 0
A19: Total for Other Current Assets | C19: =C17+C18 -> 0 | D19: =D17+D18 -> 0
A20: Total for Current Assets | C20: =C7+C13+C16+C19 -> 521077.04 | D20: =D7+D13+D16+D19 -> 175688.61
A21: Fixed Assets
A22: Computer and Hardware | C22: ='2025 BS'!B22 -> 2233.7 | D22: 2233.7
A23: Total for Fixed Assets | C23: =C21+C22 -> 2233.7 | D23: =D21+D22 -> 2233.7
A24: Other Assets
A25: Security deposits | C25: ='2025 BS'!B25 -> 5546.04 | D25: 9068.13
A26: Total for Other Assets | C26: =C24+C25 -> 5546.04 | D26: =D24+D25 -> 9068.13
A27: Total for Assets | C27: =C6+C20+C23+C26 -> 528856.78 | D27: =D6+D20+D23+D26 -> 186990.44
A28: Liabilities and Equity
A29: Liabilities
A30: Current Liabilities
A31: Credit Cards
A32: Chase - Brudnicki 8695 | B32: ='2024 BS'!B21 -> 0 | C32: ='2025 BS'!B32 -> 0 | D32: 0
A33: Chase Credit Card - United 8687 | B33: ='2024 BS'!B22 -> 4021.45 | C33: ='2025 BS'!B33 -> 49.42 | D33: 5226.16
A34: Total for Credit Cards | B34: =B31+B32+B33 -> 4021.45 | C34: =C31+C32+C33 -> 49.42 | D34: =D31+D32+D33 -> 5226.16
A35: Other Current Liabilities
A36: Commissions Due to Precision | B36: ='2024 BS'!B25 -> -45847.39 | C36: ='2025 BS'!B36 -> -281589.91 | D36: -537588.2
A37: Insurance Premiums Owed | B37: ='2024 BS'!B26 -> 175314.78 | C37: ='2025 BS'!B37 -> 788471.17 | D37: 619137.61
A38: Total for Other Current Liabilities | B38: =B35+B36+B37 -> 129467.39 | C38: =C35+C36+C37 -> 506881.26 | D38: =D35+D36+D37 -> 81549.41
A39: Total for Current Liabilities | B39: =B30+B34+B38 -> 133488.84 | C39: =C30+C34+C38 -> 506930.68 | D39: =D30+D34+D38 -> 86775.57
A40: Total for Liabilities | B40: =B29+B39 -> 133488.84 | C40: =C29+C39 -> 506930.68 | D40: =D29+D39 -> 86775.57
A41: Equity
A42: Opening balance equity | B42: ='2024 BS'!B31 -> 0 | C42: ='2025 BS'!B42 -> 0 | D42: 0
A43: Partner distributions | C43: ='2025 BS'!B43 -> 0 | D43: -60000
A44: Hannah Brudnicki | C44: ='2025 BS'!B44 -> -3051.63 | D44: -3051.63
A45: Total for Partner distributions | B45: =B43+B44 -> 0 | C45: =C43+C44 -> -3051.63 | D45: =D43+D44 -> -63051.63
A46: Retained Earnings | C46: ='2025 BS'!B46 -> 28229.32 | D46: 24977.13
A47: Net Income | B47: ='2024 BS'!B33 -> 28229.32 | C47: ='2025 BS'!B47 -> -3251.59 | D47: 138289.37
A48: Total for Equity | B48: =B41+B42+B45+B46+B47 -> 28229.32 | C48: =C41+C42+C45+C46+C47 -> 21926.1 | D48: =D41+D42+D45+D46+D47 -> 100214.87
A49: Total for Liabilities and Equity | B49: =B28+B40+B48 -> 161718.16 | C49: =C28+C40+C48 -> 528856.78 | D49: =D28+D40+D48 -> 186990.44
A51: Footnote: Precision Brokers’ balance sheet reflects both client premiums receivable and premiums payable to carriers. The portion of premiums representing commissions due to Precision is recorded as an offset against the carrier liability, reducing the total payable balance. Revenue is recognized when commissions are swept from the premium trust account to the operating account, at which point the income statement reflects earned commissions.

Sheet Trial Balance
A1: Precision Brokers, LLC
A2: Trial Balance
A3: As of Jun 30, 2026
A5: Account Name | B5: Debit | C5: Credit
A6: Chase Business Operating 2157 | B6: 117004.95
A7: Chase Premium 5805 | B7: 32739.54
A8: Operating Cash (Trust Restricted) | B8: 13293.71
A9: Operating Cash (Unrestricted) | C9: 13293.71
A10: Accounts Receivable (A/R) | B10: 25944.12
A11: Payments to deposit | C11: 0
A12: Computer and Hardware | B12: 2233.7
A13: Security deposits | B13: 9068.13
A14: Chase - Brudnicki 8695 | C14: 0
A15: Chase Credit Card - United 8687 | C15: 5226.16
A16: Commissions Due to Precision | B16: 537588.2
A17: Insurance Premiums Owed | C17: 619137.61
A18: Opening balance equity | C18: 0
A19: Partner distributions | B19: 60000
A20: Partner distributions:Hannah Brudnicki | B20: 3051.63
A21: Retained Earnings | C21: 24977.13
A22: Sales | C22: 370287.28
A23: Business licenses | B23: 1454.63
A24: Dues and Memberships | B24: 5850
A25: Employee benefits:Employee retirement plans | B25: 2300
A26: General business expenses:Bank fees & service charges | B26: 16.31
A27: General business expenses:Continuing education | B27: 5725
A28: Insurance | B28: 5995.83
A29: Legal & accounting services | B29: 97.85
A30: Legal & accounting services:Accounting fees | B30: 1875
A31: Legal & accounting services:Legal fees | B31: 2210
A32: Meals | B32: 3649.29
A33: Office expenses:Office supplies | B33: 2149.87
A34: Office expenses:Shipping & postage | B34: 2.5
... A41: Rent | B41: 5882.4
A42: Travel
A43: Travel:Airfare | B43: 8845.93
A44: Travel:Hotels | B44: 2523.87
A45: Travel:Taxis or shared rides | B45: 1068.75
A46: Vehicle expenses:Parking & tolls | B46: 175
A47: Vehicle expenses:Vehicle gas & fuel | B47: 52.15
A48: TOTAL | B48: =B6+B7+B8+B9+B10+B11+B12+B13+B14+B15+B16+B17+B18+B19+B20+B21+B22+B23+B24+B25+B26+B27+B28+B29+B30+B31+B32+B33+B34+B35+B36+B37+B38+B39+B40+B41+B42+B43+B44+B45+B46+B47 -> 1032921.9 | C48: =C6+C7+C8+C9+C10+C11+C12+C13+C14+C15+C16+C17+C18+C19+C20+C21+C22+C23+C24+C25+C26+C27+C28+C29+C30+C31+C32+C33+C34+C35+C36+C37+C38+C39+C40+C41+C42+C43+C44+C45+C46+C47 -> 1032921.9
A52: Accrual Basis Monday, August 03, 2026 10:13 AM GMT-04:00
